feisty/__init__.py
feisty/__main__.py
feisty/command_line.py
feisty/decorators.py
feisty/generate.py
feisty-0.2.3.dist-info/entry_points.txt
feisty-0.2.3.dist-info/WHEEL
feisty-0.2.3.dist-info/METADATA
feisty-0.2.3.dist-info/RECORD
